echidna/__init__.py
echidna/daug.py
echidna/utils.py
echidna-0.2.1.dist-info/LICENSE
echidna-0.2.1.dist-info/METADATA
echidna-0.2.1.dist-info/WHEEL
echidna-0.2.1.dist-info/top_level.txt
echidna-0.2.1.dist-info/RECORD
